bytedance_rooms_audio_tester/__init__.py
bytedance_rooms_audio_tester-0.0.1.dist-info/METADATA
bytedance_rooms_audio_tester-0.0.1.dist-info/WHEEL
bytedance_rooms_audio_tester-0.0.1.dist-info/top_level.txt
bytedance_rooms_audio_tester-0.0.1.dist-info/RECORD
